code_analyza/__init__.py
code_analyza/__main__.py
code_analyza/linter/__init__.py
code_analyza/linter/checks.py
code_analyza/linter/utils.py
code_analyza-0.0b1.dist-info/METADATA
code_analyza-0.0b1.dist-info/WHEEL
code_analyza-0.0b1.dist-info/licenses/LICENSE
code_analyza-0.0b1.dist-info/RECORD
