Metadata-Version: 2.1
Name: code_analyza
Version: 0.0b1
Summary: A Code Analyser package.
Project-URL: repository, https://github.com/cliftondavies/sca
Author: Clifton Davies
License: MIT License
License-File: LICENSE
Keywords: code analyser,linter,pep8
Classifier: License :: OSI Approved :: MIT License
Classifier: Operating System :: OS Independent
Classifier: Programming Language :: Python :: 3
Requires-Python: >=3.7
